s3uploader/__init__.py
s3uploader/__main__.py
s3uploader/s3uploader.py
s3uploader_ci_cd-1.0.4.dist-info/entry_points.txt
s3uploader_ci_cd-1.0.4.dist-info/LICENSE
s3uploader_ci_cd-1.0.4.dist-info/METADATA
s3uploader_ci_cd-1.0.4.dist-info/WHEEL
s3uploader_ci_cd-1.0.4.dist-info/RECORD
