Metadata-Version: 2.1
Name: s3uploader-ci-cd
Version: 1.0.4
Summary: S3 Uploader for CI/CD pipeline
Home-page: https://github.com/Mellkori/s3uploader
Author: Mellkori
Author-email: milos.slavik@outlook.com
Requires-Python: >=3.9,<4.0
Classifier: Programming Language :: Python :: 3
Classifier: Programming Language :: Python :: 3.9
Classifier: Programming Language :: Python :: 3.10
Classifier: Programming Language :: Python :: 3.11
Requires-Dist: boto3 (==1.26.122)
Requires-Dist: coverage (==7.2.3)
Requires-Dist: python-dotenv (==1.0.0)
